README.rst
development.ini
setup.cfg
setup.py
kotti_twitter/__init__.py
kotti_twitter/tests.py
kotti_twitter.egg-info/PKG-INFO
kotti_twitter.egg-info/SOURCES.txt
kotti_twitter.egg-info/dependency_links.txt
kotti_twitter.egg-info/not-zip-safe
kotti_twitter.egg-info/requires.txt
kotti_twitter.egg-info/top_level.txt
kotti_twitter/templates/profile_widget.pt
kotti_twitter/templates/search_widget.pt